{
  "parent": "minecraft:recipes/root",
  "rewards": {
    "recipes": [
      "vtones:myst_block_10"
    ]
  },
  "criteria": {
    "has_myst_block_10": {
      "trigger": "minecraft:inventory_changed",
      "conditions": {
        "items": [
          {
            "items": [
              "vtones:myst_block_10"
            ]
          }
        ]
      }
    },
    "has_the_recipe": {
      "trigger": "minecraft:recipe_unlocked",
      "conditions": {
        "recipe": "vtones:myst_block_10"
      }
    }
  },
  "requirements": [
    [
      "has_myst_block_10",
      "has_the_recipe"
    ]
  ]
}