{
  "parent": "minecraft:recipes/root",
  "rewards": {
    "recipes": [
      "vtones:zion_block_11"
    ]
  },
  "criteria": {
    "has_zion_block_11": {
      "trigger": "minecraft:inventory_changed",
      "conditions": {
        "items": [
          {
            "items": [
              "vtones:zion_block_11"
            ]
          }
        ]
      }
    },
    "has_the_recipe": {
      "trigger": "minecraft:recipe_unlocked",
      "conditions": {
        "recipe": "vtones:zion_block_11"
      }
    }
  },
  "requirements": [
    [
      "has_zion_block_11",
      "has_the_recipe"
    ]
  ]
}